<?xml version="1.0" encoding="UTF-8"?>
<prodotti>
    <prodotto>
        <nome>Dell XPS 13 Plus</nome>
        <info>Laptop leggero e potente per lavoro e studio.</info>
        <prezzo>1299.00</prezzo>
    </prodotto>
    <prodotto>
        <nome>MacBook Air M2</nome>
        <info>Notebook sottile con ottima autonomia e prestazioni fluide.</info>
        <prezzo>1399.00</prezzo>
    </prodotto>
    <prodotto>
        <nome>HP Pavilion 15</nome>
        <info>Portatile versatile adatto all’uso quotidiano.</info>
        <prezzo>799.99</prezzo>
    </prodotto>
    <prodotto>
        <nome>Lenovo ThinkPad E14</nome>
        <info>Notebook affidabile pensato per il lavoro professionale.</info>
        <prezzo>899.00</prezzo>
    </prodotto>
    <prodotto>
        <nome>Asus ROG Strix G15</nome>
        <info>Laptop gaming con hardware potente e schermo fluido.</info>
        <prezzo>1499.00</prezzo>
    </prodotto>
</prodotti>
